sql_flex
