Metadata-Version: 2.1
Name: sqlflex
Version: 0.0.3
Summary: Extract Hardcoded Value's and the related Column Names from the SQL Query
Home-page: https://github.com/shashishekhar1001/flex_sql
Author: shashishekhar
Author-email: shashishekhar1001@gmail.com
License: UNKNOWN
Platform: UNKNOWN
Classifier: Development Status :: 2 - Pre-Alpha
Classifier: Programming Language :: Python :: 3.0
Classifier: Programming Language :: Python :: 3.6
Classifier: License :: OSI Approved :: GNU General Public License v3 or later (GPLv3+)
Provides-Extra: dev
